README.txt
setup.py
dal/__init__.py
dal.egg-info/PKG-INFO
dal.egg-info/SOURCES.txt
dal.egg-info/dependency_links.txt
dal.egg-info/top_level.txt
dal.egg-info/zip-safe
dal/dbapi/__init__.py
dal/dbapi/config_MySQLdb.py
dal/dbapi/config_cx_Oracle.py
dal/dbapi/config_psycopg.py
dal/dbapi/db_row.py
dal/dbapi/dbapi.py
dal/dbapi/dbtime.py
dal/dbapi/dtuple.py
dal/dbapi/paramstyles.py
dal/dbi/__init__.py
