Metadata-Version: 1.0
Name: dal
Version: 0.2
Summary: a python database abstraction layer.
Home-page: http://pydal.sourceforge.net/
Author: Randall Smith
Author-email: randall@tnr.cc
License: BSD
Keywords: dal
Platform: UNKNOWN
